README.rst
setup.cfg
setup.py
Mathics.egg-info/PKG-INFO
Mathics.egg-info/SOURCES.txt
Mathics.egg-info/dependency_links.txt
Mathics.egg-info/entry_points.txt
Mathics.egg-info/not-zip-safe
Mathics.egg-info/requires.txt
Mathics.egg-info/top_level.txt
mathics/__init__.py
mathics/benchmark.py
mathics/main.py
mathics/manage.py
mathics/profile_mathics.py
mathics/script.py
mathics/server.py
mathics/settings.py
mathics/test.py
mathics/urls.py
mathics/version.py
mathics/algorithm/__init__.py
mathics/algorithm/clusters.py
mathics/algorithm/introselect.py
mathics/autoload/formats/CSV/Export.m
mathics/autoload/formats/CSV/Import.m
mathics/autoload/formats/Image/Export.m
mathics/autoload/formats/Image/Import.m
mathics/autoload/formats/JSON/Import.m
mathics/autoload/formats/SVG/Export.m
mathics/autoload/formats/Text/Export.m
mathics/autoload/formats/Text/Import.m
mathics/autoload/formats/XML/Import.m
mathics/builtin/__init__.py
mathics/builtin/algebra.py
mathics/builtin/arithmetic.py
mathics/builtin/assignment.py
mathics/builtin/attributes.py
mathics/builtin/base.py
mathics/builtin/calculus.py
mathics/builtin/codetables.py
mathics/builtin/colors.py
mathics/builtin/combinatorial.py
mathics/builtin/comparison.py
mathics/builtin/compilation.py
mathics/builtin/control.py
mathics/builtin/datentime.py
mathics/builtin/diffeqns.py
mathics/builtin/evaluation.py
mathics/builtin/exptrig.py
mathics/builtin/files.py
mathics/builtin/formatting.py
mathics/builtin/functional.py
mathics/builtin/graphics.py
mathics/builtin/graphics3d.py
mathics/builtin/image.py
mathics/builtin/importexport.py
mathics/builtin/inout.py
mathics/builtin/integer.py
mathics/builtin/linalg.py
mathics/builtin/lists.py
mathics/builtin/logic.py
mathics/builtin/manipulate.py
mathics/builtin/natlang.py
mathics/builtin/numbertheory.py
mathics/builtin/numeric.py
mathics/builtin/options.py
mathics/builtin/patterns.py
mathics/builtin/physchemdata.py
mathics/builtin/plot.py
mathics/builtin/randomnumbers.py
mathics/builtin/recurrence.py
mathics/builtin/scoping.py
mathics/builtin/specialfunctions.py
mathics/builtin/strings.py
mathics/builtin/structure.py
mathics/builtin/system.py
mathics/builtin/tensors.py
mathics/builtin/xmlformat.py
