Metadata-Version: 1.1
Name: Mathics
Version: 1.0
Summary: A general-purpose computer algebra system.
Home-page: https://mathics.github.io/
Author: Angus Griffith
Author-email: mathics@angusgriffith.com
License: GPL
Download-URL: https://github.com/mathics/Mathics/tarball/v0.9
Keywords: Mathematica,Wolfram,Interpreter,Shell,Math,CAS
Platform: UNKNOWN
Classifier: Intended Audience :: Developers
Classifier: Intended Audience :: Science/Research
Classifier: License :: OSI Approved :: GNU General Public License v3 (GPLv3)
Classifier: Programming Language :: Python
Classifier: Programming Language :: Python :: 2.7
Classifier: Programming Language :: Python :: 3.2
Classifier: Programming Language :: Python :: 3.3
Classifier: Programming Language :: Python :: 3.4
Classifier: Programming Language :: Python :: 3.5
Classifier: Programming Language :: Python :: Implementation :: CPython
Classifier: Programming Language :: Python :: Implementation :: PyPy
Classifier: Topic :: Scientific/Engineering
Classifier: Topic :: Scientific/Engineering :: Mathematics
Classifier: Topic :: Scientific/Engineering :: Physics
Classifier: Topic :: Software Development :: Interpreters
